bing_create/__init__.py
bing_create/main.py
bing_create-0.0.6.dist-info/METADATA
bing_create-0.0.6.dist-info/WHEEL
bing_create-0.0.6.dist-info/entry_points.txt
bing_create-0.0.6.dist-info/top_level.txt
bing_create-0.0.6.dist-info/RECORD
