Metadata-Version: 2.1
Name: bing-create
Version: 0.0.6
Summary: A simple lightweight AI Image Generator from text description using Bing Image Creator (DALL-E 3)
Home-page: https://github.com/Waenara/bing-create
Author: Waenara
Author-email: WaenaraCat@gmail.com
Project-URL: Support, https://github.com/Waenara/bing-create/issues
Keywords: ai dall-e image bing api generator bing_create image-generator ig ic
Classifier: Intended Audience :: Developers
Classifier: Topic :: Software Development :: Libraries :: Python Modules
Classifier: Programming Language :: Python :: 3.6
Classifier: Programming Language :: Python :: 3.7
Classifier: Programming Language :: Python :: 3.8
Classifier: Programming Language :: Python :: 3.9
Classifier: Programming Language :: Python :: 3.10
Classifier: Programming Language :: Python :: 3.11
Classifier: Programming Language :: Python :: 3.12
Classifier: License :: OSI Approved :: MIT License
Classifier: Operating System :: OS Independent
Requires-Python: >=3.6
Requires-Dist: setuptools~=68.2.0
Requires-Dist: aiofiles~=23.2.1
Requires-Dist: httpx~=0.27.0
